{
  "comments": [
    {
      "id": 1,
      "body": "some comment",
      "movieId": 1
    },
    {
      "username": "yo",
      "contenido": "oyo",
      "tvShowID": "1418",
      "id": 2
    },
    {
      "username": "sdfsf",
      "contenido": "sdfsf",
      "tvShowID": "1418",
      "id": 4
    },
    {
      "username": "utu",
      "contenido": "utyut",
      "tvShowID": "1418",
      "id": 6
    },
    {
      "username": "re",
      "contenido": "wer",
      "tvShowID": "1418",
      "id": 7
    },
    {
      "username": "sdgsdf",
      "contenido": "ffsd",
      "tvShowID": "1418",
      "id": 8
    },
    {
      "username": "7564",
      "contenido": "54",
      "tvShowID": "1418",
      "id": 9
    },
    {
      "username": "45",
      "contenido": "665",
      "tvShowID": "1418",
      "id": 11
    }
  ]
}